{
  "0": [
    {
      "move": "HURDLE",
      "p": 0.0392156862745098
    },
    {
      "move": "JUKE",
      "p": 0.13725490196078433
    },
    {
      "move": "PASS_THROW",
      "p": 0.43137254901960786
    },
    {
      "move": "SPIN",
      "p": 0.1568627450980392
    },
    {
      "move": "STIFF_ARM",
      "p": 0.058823529411764705
    },
    {
      "move": "WALL_MOVE",
      "p": 0.17647058823529413
    }
  ],
  "1": [
    {
      "move": "SPIN",
      "p": 0.39999999999999997
    },
    {
      "move": "STIFF_ARM",
      "p": 0.6
    }
  ],
  "12": [
    {
      "move": "PASS_THROW",
      "p": 1.0
    }
  ]
}